pyrelp
relp
