Metadata-Version: 1.0
Name: pyrelp
Version: 0.5
Summary: A python wrapper of librelp
Home-page: https://github.com/mathias-nyman/pyrelp
Author: Mathias Nyman
Author-email: UNKNOWN
License: GPLv3
Platform: UNKNOWN
